[
    {
      "names": {
        "ar": "مولاي عالي الشريف",
        "en": "MyAliCherif",
        "fr": "MyAliCherif"
      }
    },
    {
      "names": {
        "ar": "الريصاني",
        "en": "Rissani",
        "fr": "Rissani"
      }
    },
    {
      "names": {
        "ar": "أوفوس",
        "en": "Aoufous",
        "fr": "Aoufous"
      }
    },
    {
      "names": {
        "ar": "أرفود",
        "en": "Arfoud",
        "fr": "Arfoud"
      }
    },
    {
      "names": {
        "ar": "اغونان",
        "en": "Ighounane",
        "fr": "Ighounane"
      }
    },
    {
      "names": {
        "ar": "الريش",
        "en": "Er-Rich",
        "fr": "Er-Rich"
      }
    },
    {
      "names": {
        "ar": "بودنيب",
        "en": "Boudnib",
        "fr": "Boudnib"
      }
    },
    {
      "names": {
        "ar": "بومية",
        "en": "Boumia",
        "fr": "Boumia"
      }
    },
    {
      "names": {
        "ar": null,
        "en": "Errachidia",
        "fr": "Errachidia"
      }
    },
    {
      "names": {
        "ar": "تنجداد",
        "en": "Gardmit",
        "fr": "Gardmit"
      }
    },
    {
      "names": {
        "ar": "كلميمة",
        "en": "Goulmima",
        "fr": "Goulmima"
      }
    },
    {
      "names": {
        "ar": "ݣرامة",
        "en": "Gourrama",
        "fr": "Gourrama"
      }
    },
    {
      "names": {
        "ar": "إتزار",
        "en": "Itzer",
        "fr": "Itzer"
      }
    },
    {
      "names": {
        "ar": "جرف",
        "en": "Jorf",
        "fr": "Jorf"
      }
    },
    {
      "names": {
        "ar": null,
        "en": "Midelt",
        "fr": "Midelt"
      }
    },
    {
      "names": {
        "ar": null,
        "en": "Moulay Ali Cherif",
        "fr": "Moulay Ali Cherif"
      }
    },
    {
      "names": {
        "ar": "تنجداد",
        "en": "Tinejdad",
        "fr": "Tinejdad"
      }
    },
    {
      "names": {
        "ar": null,
        "en": "Tichoute",
        "fr": "Tichoute"
      }
    },
    {
      "names": {
        "ar": "تونفيت",
        "en": "Tounfite",
        "fr": "Tounfite"
      }
    },
    {
      "names": {
        "ar": "زايدة",
        "en": "Zaida",
        "fr": "Zaïda"
      }
    },
    {
      "names": {
        "ar": "أكدز",
        "en": "Agdz",
        "fr": "Agdz"
      }
    },
    {
      "names": {
        "ar": "بومالن دادس",
        "en": "Boumalne-Dades",
        "fr": "Boumalne-Dadès"
      }
    },
    {
      "names": {
        "ar": "ألنيف",
        "en": "Alnif",
        "fr": "Alnif"
      }
    },
    {
      "names": {
        "ar": "حارة اليمين",
        "en": "Harte Lyamine",
        "fr": "Harte Lyamine"
      }
    },
    {
      "names": {
        "ar": null,
        "en": "Ighil n'Oumgoun",
        "fr": "Ighil n'Oumgoun"
      }
    },
    {
      "names": {
        "ar": null,
        "en": "Imassine",
        "fr": "Imassine"
      }
    },
    {
      "names": {
        "ar": null,
        "en": "Ifri",
        "fr": "Ifri"
      }
    },
    {
      "names": {
        "ar": "آيت يالا",
        "en": "Ait Yalla",
        "fr": "Aït Yalla"
      }
    },
    {
      "names": {
        "ar": null,
        "en": "Kelaat-M'Gouna",
        "fr": "Kelaat-M'Gouna"
      }
    },
    {
      "names": {
        "ar": null,
        "en": "M'semrir",
        "fr": "M'semrir"
      }
    },
    {
      "names": {
        "ar": null,
        "en": "Sarghine",
        "fr": "Sarghine"
      }
    },
    {
      "names": {
        "ar": "سكورة",
        "en": "Skoura",
        "fr": "Skoura"
      }
    },
    {
      "names": {
        "ar": null,
        "en": "Tabounte",
        "fr": "Tabounte"
      }
    },
    {
      "names": {
        "ar": "تامكروت",
        "en": "Tamegroute",
        "fr": "Tamegroute"
      }
    },
    {
      "names": {
        "ar": null,
        "en": "Tanoumrite Nkob Zagora",
        "fr": "Tanoumrite Nkob Zagora"
      }
    },
    {
      "names": {
        "ar": null,
        "en": "Taourirt ait zaghar",
        "fr": "Taourirt ait zaghar"
      }
    },
    {
      "names": {
        "ar": "وارزازات",
        "en": "Ouarzazate",
        "fr": "Ouarzazate"
      }
    },
    {
      "names": {
        "ar": null,
        "en": "Toundoute",
        "fr": "Toundoute"
      }
    },
    {
      "names": {
        "ar": "زاݣورة",
        "en": "Zagora",
        "fr": "Zagora"
      }
    },
    {
      "names": {
        "ar": null,
        "en": "Dra'a",
        "fr": "Dra'a"
      }
    }
  ]